Metadata-Version: 1.0
Name: Gaussian-Binomial-OM
Version: 0.1
Summary: Gaussian and Binomial
Home-page: UNKNOWN
Author: UNKNOWN
Author-email: UNKNOWN
License: UNKNOWN
Platform: UNKNOWN
